CRPTBacktest/PyStrategy.py
CRPTBacktest/__init__.py
CRPTBacktest/python_simulator.cpython-312-x86_64-linux-gnu.so
crptbacktest-0.2.1.dist-info/licenses/LICENSE
crptbacktest-0.2.1.dist-info/METADATA
crptbacktest-0.2.1.dist-info/WHEEL
crptbacktest-0.2.1.dist-info/top_level.txt
crptbacktest-0.2.1.dist-info/RECORD
