Metadata-Version: 2.4
Name: CRPTBacktest
Version: 0.2.1
Summary: Tick data backtester
Author-email: Anar Faradzhov <antaresstarra@gmail.com>
Classifier: Programming Language :: Python :: 3
Classifier: License :: OSI Approved :: Apache Software License
Requires-Python: >=3.8
License-File: LICENSE
Dynamic: license-file
